mpcjax/__init__.py
mpcjax/direct_solve.py
mpcjax/dynamics_definitions.py
mpcjax/function_cache.py
mpcjax/jax_solver.py
mpcjax/optimality.py
mpcjax/problem_struct.py
mpcjax/remote.py
mpcjax/remote_like_interface.py
mpcjax/sanitize.py
mpcjax/scp_solve.py
mpcjax/second_order_solvers.py
mpcjax/solver_definitions.py
mpcjax/solver_settings.py
mpcjax/utils.py
tests/__init__.py
tests/dynamics.py
tests/test_diff_cost.py
tests/test_slew.py
tests/test_solve.py
mpcjax-0.4.0.dist-info/LICENSE
mpcjax-0.4.0.dist-info/METADATA
mpcjax-0.4.0.dist-info/WHEEL
mpcjax-0.4.0.dist-info/top_level.txt
mpcjax-0.4.0.dist-info/RECORD
