Metadata-Version: 2.1
Name: mpcjax
Version: 0.4.0
Summary: A pure-JAX, CPU or GPU Model Predictive Control solver.
Author-email: Robert Dyro <robert.dyro@gmail.com>
Project-URL: Homepage, https://github.com/rdyro/mpcjax
Project-URL: Bug Tracker, https://github.com/rdyro/mpcjax
Classifier: Programming Language :: Python :: 3
Classifier: License :: OSI Approved :: MIT License
Classifier: Operating System :: OS Independent
Requires-Python: >=3.7
License-File: LICENSE
Requires-Dist: numpy
Requires-Dist: jax
Requires-Dist: jaxfi
Requires-Dist: redis
